dealFilePoject.py
setup.py
dealFilePoject.egg-info/PKG-INFO
dealFilePoject.egg-info/SOURCES.txt
dealFilePoject.egg-info/dependency_links.txt
dealFilePoject.egg-info/top_level.txt