Metadata-Version: 1.0
Name: dealFilePoject
Version: 1.0.0
Summary: Deal data of file V1.0.0
Home-page: http://www.headfirstlabs.com
Author: wallace.wang
Author-email: wangwen5366@163.com
License: UNKNOWN
Platform: UNKNOWN
